{
    "fluentMethods": true,
    "relationships": [
        {
            "relationshipType": "many-to-one",
            "relationshipValidateRules": "required",
            "relationshipName": "driver",
            "otherEntityName": "driver",
            "otherEntityField": "fullName"
        },
        {
            "relationshipType": "many-to-one",
            "relationshipValidateRules": "required",
            "relationshipName": "passenger",
            "otherEntityName": "passenger",
            "otherEntityField": "fullName"
        }
    ],
    "fields": [
        {
            "fieldName": "status",
            "fieldType": "Boolean"
        },
        {
            "fieldName": "value",
            "fieldType": "Integer"
        }
    ],
    "changelogDate": "20170924035638",
    "entityTableName": "rating",
    "dto": "no",
    "pagination": "pagination",
    "service": "serviceClass"
}